autiobooksqta/__init__.py
autiobooksqta/__main__.py
autiobooksqta/add_on.py
autiobooksqta/audio_monitor_worker.py
autiobooksqta/autiobookspqt.py
autiobooksqta/conversion_working.py
autiobooksqta/engine_pyqt.py
autiobooksqta/ffmpeg_downloader.py
autiobooksqta/light_theme.py
autiobooksqta/output_options.py
autiobooksqta/voices_lang.py
autiobooksqta/models/en_core_web_sm-3.8.0-py3-none-any.whl
autiobooksqta-0.1.1.dist-info/LICENSE
autiobooksqta-0.1.1.dist-info/METADATA
autiobooksqta-0.1.1.dist-info/WHEEL
autiobooksqta-0.1.1.dist-info/entry_points.txt
autiobooksqta-0.1.1.dist-info/top_level.txt
autiobooksqta-0.1.1.dist-info/RECORD
